{
  "wheel-size": { "type": "size", "description": "Total wheel size" },
  "border-color": { "type": "color", "description": "Wheel ring border and accent colour" },
  "inner-border-color": { "type": "color", "description": "Inner border highlight colour" },
  "text-color": { "type": "color", "description": "Wheel item label text colour" },
  "label-color": { "type": "color", "description": "Small caption text colour (SPINS label, RESULT header)" },
  "glow-color": { "type": "color", "description": "Glow and shadow accent colour" },
  "hub-bg": { "type": "color", "description": "Centre hub background colour" },
  "hub-text": { "type": "color", "description": "Centre hub spins-owed number colour" },
  "hub-label-size": { "type": "size", "description": "Font size for the SPINS label above the spins counter" },
  "hub-count-size": { "type": "size", "description": "Font size for the spins counter number" },
  "slice-text-size": { "type": "size", "description": "Base font size for wheel item text on slices" },
  "needle-color": { "type": "color", "description": "Teardrop pointer colour" },
  "nameplate-bg": { "type": "color", "description": "Result nameplate background colour" },
  "nameplate-border": { "type": "color", "description": "Result nameplate border colour" },
  "nameplate-text": { "type": "color", "description": "Result nameplate item text colour" },
  "panelColor1": { "type": "color", "description": "One of many background colours for wheel item sections" },
  "panelColor2": { "type": "color", "description": "One of many background colours for wheel item sections" },
  "panelColor3": { "type": "color", "description": "One of many background colours for wheel item sections" },
  "panelColor4": { "type": "color", "description": "One of many background colours for wheel item sections" },
  "panelColor5": { "type": "color", "description": "One of many background colours for wheel item sections" },
  "panelColor6": { "type": "color", "description": "One of many background colours for wheel item sections" },
  "panelColor7": { "type": "color", "description": "One of many background colours for wheel item sections" },
  "panelColor8": { "type": "color", "description": "One of many background colours for wheel item sections" }
}
